PyTestStub/GenerateUnitTests.py
PyTestStub/Generator.py
PyTestStub/Templates.py
PyTestStub/__init__.py
PyTestStub-0.0.4.dist-info/LICENSE
PyTestStub-0.0.4.dist-info/METADATA
PyTestStub-0.0.4.dist-info/WHEEL
PyTestStub-0.0.4.dist-info/top_level.txt
PyTestStub-0.0.4.dist-info/RECORD
