Metadata-Version: 2.1
Name: PyTestStub
Version: 0.0.4
Summary: Reads your Python code to generate unit test stubs
Home-page: https://github.com/AgalmicVentures/PyTestStub/
Author: Ian Hutchinson
Author-email: ihutchinson@agalmicventures.com
License: MIT
Platform: UNKNOWN
Classifier: Programming Language :: Python :: 3
Classifier: License :: OSI Approved :: MIT License
Classifier: Operating System :: OS Independent
